LICENSE
README.md
setup.py
linksgpt_url_shortener/__init__.py
linksgpt_url_shortener/api_client.py
linksgpt_url_shortener/configuration.py
linksgpt_url_shortener/rest.py
linksgpt_url_shortener.egg-info/PKG-INFO
linksgpt_url_shortener.egg-info/SOURCES.txt
linksgpt_url_shortener.egg-info/dependency_links.txt
linksgpt_url_shortener.egg-info/requires.txt
linksgpt_url_shortener.egg-info/top_level.txt
linksgpt_url_shortener/api/__init__.py
linksgpt_url_shortener/api/v1_domains_api.py
linksgpt_url_shortener/api/v1_links_api.py
linksgpt_url_shortener/api/v1_users_api.py
linksgpt_url_shortener/models/__init__.py
linksgpt_url_shortener/models/inline_response200.py
linksgpt_url_shortener/models/inline_response2001.py
linksgpt_url_shortener/models/inline_response2002.py
linksgpt_url_shortener/models/inline_response2003.py
linksgpt_url_shortener/models/inline_response2004.py
linksgpt_url_shortener/models/inline_response2004_data.py
linksgpt_url_shortener/models/inline_response2005.py
linksgpt_url_shortener/models/inline_response400.py
linksgpt_url_shortener/models/v1_create_link_request.py
linksgpt_url_shortener/models/v1_domain_resource.py
linksgpt_url_shortener/models/v1_domain_resource_provider.py
linksgpt_url_shortener/models/v1_link_resource.py
linksgpt_url_shortener/models/v1_link_resource_utm.py
linksgpt_url_shortener/models/v1_re_tag_request.py
linksgpt_url_shortener/models/v1_update_link_request.py
linksgpt_url_shortener/models/v1_user_resource.py