Metadata-Version: 2.1
Name: linksgpt-url-shortener
Version: 1.0.0
Summary: LinksGPT URL Shortener Python SDK. It supports AI-driven URL shortening and expansion, custom domains, team roles, customizable QR codes, tracking and in-depth analytics, deep linking and enhanced link security.
Home-page: https://github.com/LinksGPT/url-shortener-sdk-python
Author: LinksGPT
Author-email: service@linksgpt.com
License: MIT License
Keywords: LinksGPT,URL Shortener,URL Expander,Short Link,SEO
Platform: UNKNOWN
License-File: LICENSE
